{
  "description": "An error",
  "type": "object",
  "properties": {
    "errors": {
      "type": "object",
      "properties": {
        "message": {
          "description": "The error message",
          "example": "Bad request. Missing or invalid input parameters."
        },
        "fields": {
          "description": "The error fields",
          "type": "object",
          "example": {
            "name": [
              "can't be blank"
            ],
            "color": [
              "can't be blank"
            ]
          }
        }
      }
    }
  },
  "additionalProperties": false,
  "required": [
    "errors"
  ]
}